{
  "id": "http://localhost:8888/collection/day15/index.json",
  "type": "Collection",
  "items": [
    {
      "id": "http://localhost:8888/collection/day15/0-day15/index.json",
      "type": "Manifest",
      "label": {
        "@none": [
          "0-day15"
        ]
      },
      "thumbnail": [
        {
          "id": "http://localhost:8888/collection/day15/0-day15/thumb.jpeg",
          "type": "Image"
        }
      ]
    }
  ],
  "label": {
    "@none": [
      "Day 15. Map made without using a computer"
    ]
  },
  "metadata": [
    {
      "label": {
        "@none": [
          "title"
        ]
      },
      "value": {
        "@none": [
          "Day 15. Map made without using a computer - Mexico"
        ]
      }
    },
    {
      "label": {
        "@none": [
          "Description"
        ]
      },
      "value": {
        "@none": [
          "This is a map made with chillies representing Mexico, whose official name is United States of Mexico. This is not a map of the diversity of chillies in Mexico nor the location of common ones. It is literally a map made with chillies."
        ]
      }
    },
    {
      "label": {
        "@none": [
          "license"
        ]
      },
      "value": {
        "@none": [
          "<a rel=\"license\" href=\"http://creativecommons.org/licenses/by-nc-sa/4.0/\"><img alt=\"Creative Commons License\" style=\"border-width:0\" src=\"https://i.creativecommons.org/l/by-nc-sa/4.0/88x31.png\" /></a><br />This work is licensed under a <a rel=\"license\" href=\"http://creativecommons.org/licenses/by-nc-sa/4.0/\">Creative Commons Attribution-NonCommercial-ShareAlike 4.0 International License</a>."
        ]
      }
    },
    {
      "label": {
        "@none": [
          "date"
        ]
      },
      "value": {
        "@none": [
          2021
        ]
      }
    },
    {
      "label": {
        "@none": [
          "creator"
        ]
      },
      "value": {
        "@none": [
          "Ishiba RO"
        ]
      }
    },
    {
      "label": {
        "@none": [
          "website"
        ]
      },
      "value": {
        "@none": [
          "<a href=\"http://ishiba.blogspot.com\">Blog de ishiba</a>"
        ]
      }
    },
    {
      "label": {
        "@none": [
          "software"
        ]
      },
      "value": {
        "@none": [
          "QGIS"
        ]
      }
    },
    {
      "label": {
        "@none": [
          "notes"
        ]
      },
      "value": {
        "@none": [
          "Pblicado originalmente en Twitter e Instagram."
        ]
      }
    }
  ],
  "thumbnail": [
    {
      "id": "http://localhost:8888/collection/day15/thumb.jpeg",
      "type": "Image"
    }
  ]
}